odoo/addons/ssi_timesheet_attendance/README.rst
odoo/addons/ssi_timesheet_attendance/__init__.py
odoo/addons/ssi_timesheet_attendance/__manifest__.py
odoo/addons/ssi_timesheet_attendance/menu.xml
odoo/addons/ssi_timesheet_attendance/data/hr_attendance_reason.xml
odoo/addons/ssi_timesheet_attendance/data/res_company.xml
odoo/addons/ssi_timesheet_attendance/models/__init__.py
odoo/addons/ssi_timesheet_attendance/models/hr_attendance_reason.py
odoo/addons/ssi_timesheet_attendance/models/hr_employee.py
odoo/addons/ssi_timesheet_attendance/models/hr_timesheet.py
odoo/addons/ssi_timesheet_attendance/models/hr_timesheet_attendance.py
odoo/addons/ssi_timesheet_attendance/models/hr_timesheet_attendance_schedule.py
odoo/addons/ssi_timesheet_attendance/models/hr_timesheet_daily_summary.py
odoo/addons/ssi_timesheet_attendance/models/res_company.py
odoo/addons/ssi_timesheet_attendance/models/res_config_settings.py
odoo/addons/ssi_timesheet_attendance/security/ir.model.access.csv
odoo/addons/ssi_timesheet_attendance/security/res_group_data.xml
odoo/addons/ssi_timesheet_attendance/static/description/icon.png
odoo/addons/ssi_timesheet_attendance/static/description/icon_timesheet.png
odoo/addons/ssi_timesheet_attendance/views/hr_attendance_reason_views.xml
odoo/addons/ssi_timesheet_attendance/views/hr_employee_views.xml
odoo/addons/ssi_timesheet_attendance/views/hr_timesheet_attendance_views.xml
odoo/addons/ssi_timesheet_attendance/views/hr_timesheet_views.xml
odoo/addons/ssi_timesheet_attendance/views/res_config_settings_view.xml
odoo/addons/ssi_timesheet_attendance/views/resource_calendar_views.xml
odoo14_addon_ssi_timesheet_attendance-14.0.1.15.0.dist-info/METADATA
odoo14_addon_ssi_timesheet_attendance-14.0.1.15.0.dist-info/WHEEL
odoo14_addon_ssi_timesheet_attendance-14.0.1.15.0.dist-info/top_level.txt
odoo14_addon_ssi_timesheet_attendance-14.0.1.15.0.dist-info/RECORD
