Metadata-Version: 2.1
Name: odoo14-addon-ssi_timesheet_attendance
Version: 14.0.1.15.0
Summary: Timesheet Attendance
Home-page: https://simetri-sinergi.id
Author: OpenSynergy Indonesia, PT. Simetri Sinergi Indonesia
License: AGPL-3
Classifier: Programming Language :: Python
Classifier: Framework :: Odoo
Classifier: Framework :: Odoo :: 14.0
Classifier: License :: OSI Approved :: GNU Affero General Public License v3
Requires-Python: >=3.6
Requires-Dist: odoo14-addon-base-public-holiday
Requires-Dist: odoo14-addon-ssi-duration-mixin
Requires-Dist: odoo14-addon-ssi-timesheet
Requires-Dist: odoo<14.1dev,>=14.0a
